[
  { "date": "2026-07-25", "source": "meta", "region": "NATIONWIDE", "provider": "IndiHome", "value": 41.0 },
  { "date": "2026-08-15", "source": "meta", "region": "NATIONWIDE", "provider": "IndiHome", "value": 41.9 },
  { "date": "2026-08-21", "source": "meta", "region": "NATIONWIDE", "provider": "IndiHome", "value": 42.8 },
  { "date": "2026-07-25", "source": "meta", "region": "NATIONWIDE", "provider": "XL Home", "value": 25.0 },
  { "date": "2026-08-15", "source": "meta", "region": "NATIONWIDE", "provider": "XL Home", "value": 25.4 },
  { "date": "2026-08-21", "source": "meta", "region": "NATIONWIDE", "provider": "XL Home", "value": 25.8 },
  { "date": "2026-07-25", "source": "meta", "region": "NATIONWIDE", "provider": "Biznet", "value": 17.0 },
  { "date": "2026-08-15", "source": "meta", "region": "NATIONWIDE", "provider": "Biznet", "value": 16.7 },
  { "date": "2026-08-21", "source": "meta", "region": "NATIONWIDE", "provider": "Biznet", "value": 16.4 },

  { "date": "2026-07-25", "source": "meta", "region": "REGIONALWIDE", "provider": "IndiHome", "value": 37.72 },
  { "date": "2026-08-15", "source": "meta", "region": "REGIONALWIDE", "provider": "IndiHome", "value": 38.55 },
  { "date": "2026-08-21", "source": "meta", "region": "REGIONALWIDE", "provider": "IndiHome", "value": 39.38 },
  { "date": "2026-07-25", "source": "meta", "region": "REGIONALWIDE", "provider": "XL Home", "value": 23.0 },
  { "date": "2026-08-15", "source": "meta", "region": "REGIONALWIDE", "provider": "XL Home", "value": 23.37 },
  { "date": "2026-08-21", "source": "meta", "region": "REGIONALWIDE", "provider": "XL Home", "value": 23.74 },
  { "date": "2026-07-25", "source": "meta", "region": "REGIONALWIDE", "provider": "Biznet", "value": 15.64 },
  { "date": "2026-08-15", "source": "meta", "region": "REGIONALWIDE", "provider": "Biznet", "value": 15.36 },
  { "date": "2026-08-21", "source": "meta", "region": "REGIONALWIDE", "provider": "Biznet", "value": 15.08 },

  { "date": "2026-07-25", "source": "meta", "region": "CITYWIDE", "provider": "IndiHome", "value": 34.85 },
  { "date": "2026-08-15", "source": "meta", "region": "CITYWIDE", "provider": "IndiHome", "value": 35.62 },
  { "date": "2026-08-21", "source": "meta", "region": "CITYWIDE", "provider": "IndiHome", "value": 36.38 },
  { "date": "2026-07-25", "source": "meta", "region": "CITYWIDE", "provider": "XL Home", "value": 21.25 },
  { "date": "2026-08-15", "source": "meta", "region": "CITYWIDE", "provider": "XL Home", "value": 21.59 },
  { "date": "2026-08-21", "source": "meta", "region": "CITYWIDE", "provider": "XL Home", "value": 21.93 },
  { "date": "2026-07-25", "source": "meta", "region": "CITYWIDE", "provider": "Biznet", "value": 14.45 },
  { "date": "2026-08-15", "source": "meta", "region": "CITYWIDE", "provider": "Biznet", "value": 14.19 },
  { "date": "2026-08-21", "source": "meta", "region": "CITYWIDE", "provider": "Biznet", "value": 13.94 },

  { "date": "2026-07-25", "source": "ookla", "region": "NATIONWIDE", "provider": "IndiHome", "value": 20.0 },
  { "date": "2026-08-15", "source": "ookla", "region": "NATIONWIDE", "provider": "IndiHome", "value": 20.9 },
  { "date": "2026-08-21", "source": "ookla", "region": "NATIONWIDE", "provider": "IndiHome", "value": 21.8 },
  { "date": "2026-07-25", "source": "ookla", "region": "NATIONWIDE", "provider": "XL Home", "value": 22.0 },
  { "date": "2026-08-15", "source": "ookla", "region": "NATIONWIDE", "provider": "XL Home", "value": 22.4 },
  { "date": "2026-08-21", "source": "ookla", "region": "NATIONWIDE", "provider": "XL Home", "value": 22.8 },
  { "date": "2026-07-25", "source": "ookla", "region": "NATIONWIDE", "provider": "Biznet", "value": 36.0 },
  { "date": "2026-08-15", "source": "ookla", "region": "NATIONWIDE", "provider": "Biznet", "value": 35.7 },
  { "date": "2026-08-21", "source": "ookla", "region": "NATIONWIDE", "provider": "Biznet", "value": 35.4 },

  { "date": "2026-07-25", "source": "ookla", "region": "REGIONALWIDE", "provider": "IndiHome", "value": 18.4 },
  { "date": "2026-08-15", "source": "ookla", "region": "REGIONALWIDE", "provider": "IndiHome", "value": 19.23 },
  { "date": "2026-08-21", "source": "ookla", "region": "REGIONALWIDE", "provider": "IndiHome", "value": 20.06 },
  { "date": "2026-07-25", "source": "ookla", "region": "REGIONALWIDE", "provider": "XL Home", "value": 20.24 },
  { "date": "2026-08-15", "source": "ookla", "region": "REGIONALWIDE", "provider": "XL Home", "value": 20.61 },
  { "date": "2026-08-21", "source": "ookla", "region": "REGIONALWIDE", "provider": "XL Home", "value": 20.98 },
  { "date": "2026-07-25", "source": "ookla", "region": "REGIONALWIDE", "provider": "Biznet", "value": 33.12 },
  { "date": "2026-08-15", "source": "ookla", "region": "REGIONALWIDE", "provider": "Biznet", "value": 32.84 },
  { "date": "2026-08-21", "source": "ookla", "region": "REGIONALWIDE", "provider": "Biznet", "value": 32.56 },

  { "date": "2026-07-25", "source": "ookla", "region": "CITYWIDE", "provider": "IndiHome", "value": 17.0 },
  { "date": "2026-08-15", "source": "ookla", "region": "CITYWIDE", "provider": "IndiHome", "value": 17.77 },
  { "date": "2026-08-21", "source": "ookla", "region": "CITYWIDE", "provider": "IndiHome", "value": 18.53 },
  { "date": "2026-07-25", "source": "ookla", "region": "CITYWIDE", "provider": "XL Home", "value": 18.7 },
  { "date": "2026-08-15", "source": "ookla", "region": "CITYWIDE", "provider": "XL Home", "value": 19.04 },
  { "date": "2026-08-21", "source": "ookla", "region": "CITYWIDE", "provider": "XL Home", "value": 19.38 },
  { "date": "2026-07-25", "source": "ookla", "region": "CITYWIDE", "provider": "Biznet", "value": 30.6 },
  { "date": "2026-08-15", "source": "ookla", "region": "CITYWIDE", "provider": "Biznet", "value": 30.34 },
  { "date": "2026-08-21", "source": "ookla", "region": "CITYWIDE", "provider": "Biznet", "value": 30.08 },

  { "date": "2026-07-25", "source": "onx", "region": "NATIONWIDE", "provider": "IndiHome", "value": 30.0 },
  { "date": "2026-08-15", "source": "onx", "region": "NATIONWIDE", "provider": "IndiHome", "value": 30.9 },
  { "date": "2026-08-21", "source": "onx", "region": "NATIONWIDE", "provider": "IndiHome", "value": 31.8 },
  { "date": "2026-07-25", "source": "onx", "region": "NATIONWIDE", "provider": "XL Home", "value": 24.0 },
  { "date": "2026-08-15", "source": "onx", "region": "NATIONWIDE", "provider": "XL Home", "value": 24.4 },
  { "date": "2026-08-21", "source": "onx", "region": "NATIONWIDE", "provider": "XL Home", "value": 24.8 },
  { "date": "2026-07-25", "source": "onx", "region": "NATIONWIDE", "provider": "Biznet", "value": 19.0 },
  { "date": "2026-08-15", "source": "onx", "region": "NATIONWIDE", "provider": "Biznet", "value": 18.7 },
  { "date": "2026-08-21", "source": "onx", "region": "NATIONWIDE", "provider": "Biznet", "value": 18.4 },

  { "date": "2026-07-25", "source": "onx", "region": "REGIONALWIDE", "provider": "IndiHome", "value": 27.6 },
  { "date": "2026-08-15", "source": "onx", "region": "REGIONALWIDE", "provider": "IndiHome", "value": 28.43 },
  { "date": "2026-08-21", "source": "onx", "region": "REGIONALWIDE", "provider": "IndiHome", "value": 29.26 },
  { "date": "2026-07-25", "source": "onx", "region": "REGIONALWIDE", "provider": "XL Home", "value": 22.08 },
  { "date": "2026-08-15", "source": "onx", "region": "REGIONALWIDE", "provider": "XL Home", "value": 22.45 },
  { "date": "2026-08-21", "source": "onx", "region": "REGIONALWIDE", "provider": "XL Home", "value": 22.82 },
  { "date": "2026-07-25", "source": "onx", "region": "REGIONALWIDE", "provider": "Biznet", "value": 17.48 },
  { "date": "2026-08-15", "source": "onx", "region": "REGIONALWIDE", "provider": "Biznet", "value": 17.2 },
  { "date": "2026-08-21", "source": "onx", "region": "REGIONALWIDE", "provider": "Biznet", "value": 16.92 },

  { "date": "2026-07-25", "source": "onx", "region": "CITYWIDE", "provider": "IndiHome", "value": 25.5 },
  { "date": "2026-08-15", "source": "onx", "region": "CITYWIDE", "provider": "IndiHome", "value": 26.27 },
  { "date": "2026-08-21", "source": "onx", "region": "CITYWIDE", "provider": "IndiHome", "value": 27.03 },
  { "date": "2026-07-25", "source": "onx", "region": "CITYWIDE", "provider": "XL Home", "value": 20.4 },
  { "date": "2026-08-15", "source": "onx", "region": "CITYWIDE", "provider": "XL Home", "value": 20.74 },
  { "date": "2026-08-21", "source": "onx", "region": "CITYWIDE", "provider": "XL Home", "value": 21.08 },
  { "date": "2026-07-25", "source": "onx", "region": "CITYWIDE", "provider": "Biznet", "value": 16.15 },
  { "date": "2026-08-15", "source": "onx", "region": "CITYWIDE", "provider": "Biznet", "value": 15.9 },
  { "date": "2026-08-21", "source": "onx", "region": "CITYWIDE", "provider": "Biznet", "value": 15.65 }
]